{
	"countor": {
		"stroke": 3,
		"fill": "white"
	},
	"eye": {
		"width": 200,
		"height": 40,
		"sclera": {
			"top": {
				"x": -49,
				"y": -117
			},
			"bottom": {
				"x": 39,
				"y": 70
			},
			"right": {
				"x": 44,
				"y": 47
			},
			"left": {
				"x": -57,
				"y": 31
			},
			"controls": [
				36,
				59,
				48,
				79,
				69,
				71,
				61,
				77
			],
			"stroke": 1,
			"color": "white"
		},
		"pupil": {
			"top": {
				"x": 0,
				"y": -30
			},
			"bottom": {
				"x": 0,
				"y": 30
			},
			"right": {
				"x": 30,
				"y": 0
			},
			"left": {
				"x": -30,
				"y": 0
			},
			"controls": [
				20,
				20,
				20,
				20,
				20,
				20,
				20,
				20
			],
			"color": "black"
		}
	},
	"mouth": {
		"width": 190,
		"height": 157,
		"topControl": {
			"x": 39,
			"y": 25
		},
		"bottomControl": {
			"x": -46,
			"y": -28
		},
		"stroke": 1,
		"color": "white"
	},
	"ear": {
		"enable": true,
		"start": {
			"deg": -19,
			"control": {
				"x": 30,
				"y": -8
			}
		},
		"end": {
			"deg": -2,
			"control": {
				"x": 49,
				"y": 23
			}
		},
		"stroke": 1,
		"color": "white"
	}
}