{
	"countor": {
		"stroke": 3,
		"fill": "white"
	},
	"eye": {
		"width": 189,
		"height": 58,
		"sclera": {
			"top": {
				"x": -1,
				"y": -72
			},
			"bottom": {
				"x": -35,
				"y": 51
			},
			"right": {
				"x": 108,
				"y": 2
			},
			"left": {
				"x": -95,
				"y": -4
			},
			"controls": [
				44,
				60,
				16,
				41,
				32,
				80,
				53,
				25
			],
			"stroke": 1,
			"color": "white"
		},
		"pupil": {
			"top": {
				"x": 0,
				"y": -30
			},
			"bottom": {
				"x": 0,
				"y": 30
			},
			"right": {
				"x": 30,
				"y": 0
			},
			"left": {
				"x": -30,
				"y": 0
			},
			"controls": [
				20,
				20,
				20,
				20,
				20,
				20,
				20,
				20
			],
			"color": "black"
		}
	},
	"mouth": {
		"width": 196,
		"height": 151,
		"topControl": {
			"x": 10,
			"y": 19
		},
		"bottomControl": {
			"x": 143,
			"y": 62
		},
		"stroke": 1,
		"color": "white"
	},
	"ear": {
		"enable": false,
		"start": {
			"deg": null,
			"control": {
				"x": null,
				"y": null
			}
		},
		"end": {
			"deg": null,
			"control": {
				"x": null,
				"y": null
			}
		},
		"stroke": 1,
		"color": "white"
	}
}